emphon/__init__.py
emphon/__main__.py
emphon/emphon.py
emphon/ipa_key.json
emphon/transcriber.py
emphon/version.py
emphon-1.3.1.dist-info/LICENSE
emphon-1.3.1.dist-info/METADATA
emphon-1.3.1.dist-info/WHEEL
emphon-1.3.1.dist-info/entry_points.txt
emphon-1.3.1.dist-info/top_level.txt
emphon-1.3.1.dist-info/RECORD
