Metadata-Version: 2.1
Name: emphon
Version: 1.3.1
Summary: A phonetic transcriber module for emtsv
Home-page: https://github.com/levaid/emPhon
Author: levaid
License: UNKNOWN
Platform: UNKNOWN
Classifier: Programming Language :: Python :: 3
Classifier: License :: OSI Approved :: GNU Lesser General Public License v3 (LGPLv3)
Classifier: Operating System :: POSIX :: Linux
Requires-Python: >=3.6
Requires-Dist: xtsv (<2.0.0,>=1.0.0)
